[
  {
    "nome": "Yeji",
    "grupo": "ITZY",
    "empresa": "JYP Entertainment",
    "ano_nascimento": 2000,
    "nacionalidade": "Coreana",
    "posicao": [
      "Leader",
      "Lead Vocal",
      "Main Dancer"
    ],
    "altura_cm": 167
  },
  {
    "nome": "Lia",
    "grupo": "ITZY",
    "empresa": "JYP Entertainment",
    "ano_nascimento": 2000,
    "nacionalidade": "Coreana",
    "posicao": [
      "Main Vocal"
    ],
    "altura_cm": 162
  },
  {
    "nome": "Ryujin",
    "grupo": "ITZY",
    "empresa": "JYP Entertainment",
    "ano_nascimento": 2001,
    "nacionalidade": "Coreana",
    "posicao": [
      "Main Rapper",
      "Lead Dancer"
    ],
    "altura_cm": 164
  },
  {
    "nome": "Chaeryeong",
    "grupo": "ITZY",
    "empresa": "JYP Entertainment",
    "ano_nascimento": 2001,
    "nacionalidade": "Coreana",
    "posicao": [
      "Main Dancer",
      "Vocal"
    ],
    "altura_cm": 166
  },
  {
    "nome": "Yuna",
    "grupo": "ITZY",
    "empresa": "JYP Entertainment",
    "ano_nascimento": 2003,
    "nacionalidade": "Coreana",
    "posicao": [
      "Visual",
      "Maknae",
      "Lead Rapper"
    ],
    "altura_cm": 170
  },
  {
    "nome": "HeeJin",
    "grupo": "LOONA",
    "empresa": "BlockBerry Creative",
    "ano_nascimento": 2000,
    "nacionalidade": "Coreana",
    "posicao": [
      "Vocal",
      "Dancer",
      "Center"
    ],
    "altura_cm": 161
  },
  {
    "nome": "HyunJin",
    "grupo": "LOONA",
    "empresa": "BlockBerry Creative",
    "ano_nascimento": 2000,
    "nacionalidade": "Coreana",
    "posicao": [
      "Vocal",
      "Dancer"
    ],
    "altura_cm": 163
  },
  {
    "nome": "HaSeul",
    "grupo": "LOONA",
    "empresa": "BlockBerry Creative",
    "ano_nascimento": 1997,
    "nacionalidade": "Coreana",
    "posicao": [
      "Leader",
      "Vocal"
    ],
    "altura_cm": 159
  },
  {
    "nome": "YeoJin",
    "grupo": "LOONA",
    "empresa": "BlockBerry Creative",
    "ano_nascimento": 2002,
    "nacionalidade": "Coreana",
    "posicao": [
      "Vocal",
      "Rapper"
    ],
    "altura_cm": 149
  },
  {
    "nome": "ViVi",
    "grupo": "LOONA",
    "empresa": "BlockBerry Creative",
    "ano_nascimento": 1996,
    "nacionalidade": "Chinesa",
    "posicao": [
      "Vocal"
    ],
    "altura_cm": 160
  },
  {
    "nome": "Kim Lip",
    "grupo": "LOONA",
    "empresa": "BlockBerry Creative",
    "ano_nascimento": 1999,
    "nacionalidade": "Coreana",
    "posicao": [
      "Vocal"
    ],
    "altura_cm": 163
  },
  {
    "nome": "JinSoul",
    "grupo": "LOONA",
    "empresa": "BlockBerry Creative",
    "ano_nascimento": 1997,
    "nacionalidade": "Coreana",
    "posicao": [
      "Vocal",
      "Rapper"
    ],
    "altura_cm": 165
  },
  {
    "nome": "Choerry",
    "grupo": "LOONA",
    "empresa": "BlockBerry Creative",
    "ano_nascimento": 2001,
    "nacionalidade": "Coreana",
    "posicao": [
      "Vocal",
      "Dancer"
    ],
    "altura_cm": 163
  },
  {
    "nome": "Yves",
    "grupo": "LOONA",
    "empresa": "BlockBerry Creative",
    "ano_nascimento": 1997,
    "nacionalidade": "Coreana",
    "posicao": [
      "Vocal",
      "Dancer"
    ],
    "altura_cm": 166
  },
  {
    "nome": "Chuu",
    "grupo": "LOONA",
    "empresa": "BlockBerry Creative",
    "ano_nascimento": 1999,
    "nacionalidade": "Coreana",
    "posicao": [
      "Main Vocal",
      "Face Of The Group"
    ],
    "altura_cm": 161
  },
  {
    "nome": "Go Won",
    "grupo": "LOONA",
    "empresa": "BlockBerry Creative",
    "ano_nascimento": 2000,
    "nacionalidade": "Coreana",
    "posicao": [
      "Vocal",
      "Rapper"
    ],
    "altura_cm": 160
  },
  {
    "nome": "Olivia Hye",
    "grupo": "LOONA",
    "empresa": "BlockBerry Creative",
    "ano_nascimento": 2001,
    "nacionalidade": "Coreana",
    "posicao": [
      "Vocal",
      "Dancer"
    ],
    "altura_cm": 165
  },
  {
    "nome": "Lily",
    "grupo": "NMIXX",
    "empresa": "JYP Entertainment",
    "ano_nascimento": 2002,
    "nacionalidade": "Coreana-Australiana",
    "posicao": [
      "Main Vocal"
    ],
    "altura_cm": 163
  },
  {
    "nome": "Haewon",
    "grupo": "NMIXX",
    "empresa": "JYP Entertainment",
    "ano_nascimento": 2003,
    "nacionalidade": "Coreana",
    "posicao": [
      "Leader",
      "Main Vocal",
      "Lead Dancer"
    ],
    "altura_cm": 162
  },
  {
    "nome": "Sullyoon",
    "grupo": "NMIXX",
    "empresa": "JYP Entertainment",
    "ano_nascimento": 2004,
    "nacionalidade": "Coreana",
    "posicao": [
      "Lead Vocal",
      "Visual",
      "Dancer"
    ],
    "altura_cm": 167
  },
  {
    "nome": "Bae",
    "grupo": "NMIXX",
    "empresa": "JYP Entertainment",
    "ano_nascimento": 2004,
    "nacionalidade": "Coreana",
    "posicao": [
      "Lead Dancer",
      "Lead Vocal"
    ],
    "altura_cm": 170
  },
  {
    "nome": "Jiwoo",
    "grupo": "NMIXX",
    "empresa": "JYP Entertainment",
    "ano_nascimento": 2005,
    "nacionalidade": "Coreana",
    "posicao": [
      "Main Rapper",
      "Main Dancer",
      "Vocal"
    ],
    "altura_cm": 161
  },
  {
    "nome": "Kyujin",
    "grupo": "NMIXX",
    "empresa": "JYP Entertainment",
    "ano_nascimento": 2006,
    "nacionalidade": "Coreana",
    "posicao": [
      "Main Dancer",
      "Lead Rapper",
      "Maknae"
    ],
    "altura_cm": 164
  },
  {
    "nome": "Saerom",
    "grupo": "fromis_9",
    "empresa": "Pledis Entertainment (HYBE)",
    "ano_nascimento": 1997,
    "nacionalidade": "Coreana",
    "posicao": [
      "Leader",
      "Visual",
      "Lead Dancer"
    ],
    "altura_cm": 163
  },
  {
    "nome": "Hayoung",
    "grupo": "fromis_9",
    "empresa": "Pledis Entertainment (HYBE)",
    "ano_nascimento": 1997,
    "nacionalidade": "Coreana",
    "posicao": [
      "Main Vocal",
      "Main Dancer"
    ],
    "altura_cm": 163
  },
  {
    "nome": "Gyuri",
    "grupo": "fromis_9",
    "empresa": "Pledis Entertainment (HYBE)",
    "ano_nascimento": 1997,
    "nacionalidade": "Coreana",
    "posicao": [
      "Lead Vocal",
      "Face of The Group"
    ],
    "altura_cm": 168
  },
  {
    "nome": "Jiwon",
    "grupo": "fromis_9",
    "empresa": "Pledis Entertainment (HYBE)",
    "ano_nascimento": 1998,
    "nacionalidade": "Coreana",
    "posicao": [
      "Main Vocal"
    ],
    "altura_cm": 157
  },
  {
    "nome": "Jisun",
    "grupo": "fromis_9",
    "empresa": "Pledis Entertainment (HYBE)",
    "ano_nascimento": 1998,
    "nacionalidade": "Coreana",
    "posicao": [
      "Vocal"
    ],
    "altura_cm": 158
  },
  {
    "nome": "Seoyeon",
    "grupo": "fromis_9",
    "empresa": "Pledis Entertainment (HYBE)",
    "ano_nascimento": 2000,
    "nacionalidade": "Coreana",
    "posicao": [
      "Main Rapper",
      "Lead Vocal",
      "Main Dancer"
    ],
    "altura_cm": 158
  },
  {
    "nome": "Chaeyoung",
    "grupo": "fromis_9",
    "empresa": "Pledis Entertainment (HYBE)",
    "ano_nascimento": 2000,
    "nacionalidade": "Coreana",
    "posicao": [
      "Lead Rapper",
      "Lead Dancer",
      "Vocal"
    ],
    "altura_cm": 168
  },
  {
    "nome": "Nagyung",
    "grupo": "fromis_9",
    "empresa": "Pledis Entertainment (HYBE)",
    "ano_nascimento": 2000,
    "nacionalidade": "Coreana",
    "posicao": [
      "Lead Vocal",
      "Visual"
    ],
    "altura_cm": 160
  },
  {
    "nome": "Jiheon",
    "grupo": "fromis_9",
    "empresa": "Pledis Entertainment (HYBE)",
    "ano_nascimento": 2003,
    "nacionalidade": "Coreana",
    "posicao": [
      "Vocal",
      "Maknae"
    ],
    "altura_cm": 166
  },
  {
    "nome": "Sakura",
    "grupo": "LE SSERAFIM",
    "empresa": "Source Music (HYBE)",
    "ano_nascimento": 1998,
    "nacionalidade": "Japonesa",
    "posicao": [
      "Vocal",
      "Rapper",
      "Dancer"
    ],
    "altura_cm": 163
  },
  {
    "nome": "Chaewon",
    "grupo": "LE SSERAFIM",
    "empresa": "Source Music (HYBE)",
    "ano_nascimento": 2000,
    "nacionalidade": "Coreana",
    "posicao": [
      "Leader",
      "Lead Vocal",
      "Lead Dancer"
    ],
    "altura_cm": 164
  },
  {
    "nome": "Yunjin",
    "grupo": "LE SSERAFIM",
    "empresa": "Source Music (HYBE)",
    "ano_nascimento": 2001,
    "nacionalidade": "Coreana-Americana",
    "posicao": [
      "Main Vocal",
      "Lead Dancer"
    ],
    "altura_cm": 172
  },
  {
    "nome": "Kazuha",
    "grupo": "LE SSERAFIM",
    "empresa": "Source Music (HYBE)",
    "ano_nascimento": 2003,
    "nacionalidade": "Japonesa",
    "posicao": [
      "Main Dancer",
      "Main Rapper"
    ],
    "altura_cm": 170
  },
  {
    "nome": "Eunchae",
    "grupo": "LE SSERAFIM",
    "empresa": "Source Music (HYBE)",
    "ano_nascimento": 2006,
    "nacionalidade": "Coreana",
    "posicao": [
      "Maknae",
      "Dancer",
      "Vocal"
    ],
    "altura_cm": 169
  },
  {
    "nome": "Karina",
    "grupo": "aespa",
    "empresa": "SM Entertainment",
    "ano_nascimento": 2000,
    "nacionalidade": "Coreana",
    "posicao": [
      "Leader",
      "Visual",
      "Main Dancer"
    ],
    "altura_cm": 168
  },
  {
    "nome": "Giselle",
    "grupo": "aespa",
    "empresa": "SM Entertainment",
    "ano_nascimento": 2000,
    "nacionalidade": "Japonesa-Coreana",
    "posicao": [
      "Main Rapper"
    ],
    "altura_cm": 163
  },
  {
    "nome": "Winter",
    "grupo": "aespa",
    "empresa": "SM Entertainment",
    "ano_nascimento": 2001,
    "nacionalidade": "Coreana",
    "posicao": [
      "Main Vocal",
      "Lead Dancer",
      "Visual"
    ],
    "altura_cm": 163
  },
  {
    "nome": "Ningning",
    "grupo": "aespa",
    "empresa": "SM Entertainment",
    "ano_nascimento": 2002,
    "nacionalidade": "Chinesa",
    "posicao": [
      "Main Vocal",
      "Maknae"
    ],
    "altura_cm": 161
  },
  {
    "nome": "Rei",
    "grupo": "IVE",
    "empresa": "Starship Entertainment",
    "ano_nascimento": 2004,
    "nacionalidade": "Japonesa",
    "posicao": [
      "Main Rapper"
    ],
    "altura_cm": 170
  },
  {
    "nome": "Yujin",
    "grupo": "IVE",
    "empresa": "Starship Entertainment",
    "ano_nascimento": 2003,
    "nacionalidade": "Coreana",
    "posicao": [
      "Leader",
      "Main Vocal",
      "Main Dancer"
    ],
    "altura_cm": 173
  },
  {
    "nome": "Gaeul",
    "grupo": "IVE",
    "empresa": "Starship Entertainment",
    "ano_nascimento": 2002,
    "nacionalidade": "Coreana",
    "posicao": [
      "Lead Rapper",
      "Main Dancer"
    ],
    "altura_cm": 164
  },
  {
    "nome": "Wonyoung",
    "grupo": "IVE",
    "empresa": "Starship Entertainment",
    "ano_nascimento": 2004,
    "nacionalidade": "Coreana",
    "posicao": [
      "Vocal",
      "Visual"
    ],
    "altura_cm": 173
  },
  {
    "nome": "Liz",
    "grupo": "IVE",
    "empresa": "Starship Entertainment",
    "ano_nascimento": 2004,
    "nacionalidade": "Coreana",
    "posicao": [
      "Main Vocal"
    ],
    "altura_cm": 171
  },
  {
    "nome": "Leeseo",
    "grupo": "IVE",
    "empresa": "Starship Entertainment",
    "ano_nascimento": 2007,
    "nacionalidade": "Coreana",
    "posicao": [
      "Maknae",
      "Vocal"
    ],
    "altura_cm": 165
  },
  {
    "nome": "Na Goeun",
    "grupo": "Purple Kiss",
    "empresa": "RBW Entertainment",
    "ano_nascimento": 1999,
    "nacionalidade": "Coreana",
    "posicao": [
      "Main Vocal",
      "Lead Dancer"
    ],
    "altura_cm": 161
  },
  {
    "nome": "Dosie",
    "grupo": "Purple Kiss",
    "empresa": "RBW Entertainment",
    "ano_nascimento": 2000,
    "nacionalidade": "Coreana",
    "posicao": [
      "Vocal",
      "Main Dancer"
    ],
    "altura_cm": 163
  },
  {
    "nome": "Ireh",
    "grupo": "Purple Kiss",
    "empresa": "RBW Entertainment",
    "ano_nascimento": 2002,
    "nacionalidade": "Coreana",
    "posicao": [
      "Main Dancer",
      "Vocal"
    ],
    "altura_cm": 164
  },
  {
    "nome": "Yuki",
    "grupo": "Purple Kiss",
    "empresa": "RBW Entertainment",
    "ano_nascimento": 2002,
    "nacionalidade": "Japonesa",
    "posicao": [
      "Main Rapper",
      "Lead Dancer"
    ],
    "altura_cm": 164
  },
  {
    "nome": "Chaein",
    "grupo": "Purple Kiss",
    "empresa": "RBW Entertainment",
    "ano_nascimento": 2002,
    "nacionalidade": "Coreana",
    "posicao": [
      "Main Vocal",
      "Lead Rapper",
      "Lead Dancer"
    ],
    "altura_cm": 160
  },
  {
    "nome": "Swan",
    "grupo": "Purple Kiss",
    "empresa": "RBW Entertainment",
    "ano_nascimento": 2003,
    "nacionalidade": "Coreana",
    "posicao": [
      "Main Vocal",
      "Maknae"
    ],
    "altura_cm": 165
  },
  {
    "nome": "Sumin",
    "grupo": "STAYC",
    "empresa": "High Up Entertainment",
    "ano_nascimento": 2001,
    "nacionalidade": "Coreana",
    "posicao": [
      "Leader",
      "Vocal",
      "Lead Rapper"
    ],
    "altura_cm": 159
  },
  {
    "nome": "Sieun",
    "grupo": "STAYC",
    "empresa": "High Up Entertainment",
    "ano_nascimento": 2001,
    "nacionalidade": "Coreana",
    "posicao": [
      "Main Vocal",
      "Lead Rapper",
      "Dancer"
    ],
    "altura_cm": 159
  },
  {
    "nome": "Isa",
    "grupo": "STAYC",
    "empresa": "High Up Entertainment",
    "ano_nascimento": 2002,
    "nacionalidade": "Coreana",
    "posicao": [
      "Lead Vocal",
      "Dancer"
    ],
    "altura_cm": 165
  },
  {
    "nome": "Seeun",
    "grupo": "STAYC",
    "empresa": "High Up Entertainment",
    "ano_nascimento": 2003,
    "nacionalidade": "Coreana",
    "posicao": [
      "Vocal"
    ],
    "altura_cm": 167
  },
  {
    "nome": "Yoon",
    "grupo": "STAYC",
    "empresa": "High Up Entertainment",
    "ano_nascimento": 2004,
    "nacionalidade": "Coreana",
    "posicao": [
      "Lead Vocal"
    ],
    "altura_cm": 172
  },
  {
    "nome": "J",
    "grupo": "STAYC",
    "empresa": "High Up Entertainment",
    "ano_nascimento": 2004,
    "nacionalidade": "Coreana",
    "posicao": [
      "Maknae",
      "Vocal",
      "Main Rapper"
    ],
    "altura_cm": 169
  },
  {
    "nome": "Minji",
    "grupo": "NewJeans",
    "empresa": "ADOR (HYBE)",
    "ano_nascimento": 2004,
    "nacionalidade": "Coreana",
    "posicao": [
      "Vocal",
      "Visual",
      "Rapper"
    ],
    "altura_cm": 169
  },
  {
    "nome": "Hanni",
    "grupo": "NewJeans",
    "empresa": "ADOR (HYBE)",
    "ano_nascimento": 2004,
    "nacionalidade": "Vietnamita-Australiana",
    "posicao": [
      "Main Vocal",
      "Main Dancer"
    ],
    "altura_cm": 162
  },
  {
    "nome": "Danielle",
    "grupo": "NewJeans",
    "empresa": "ADOR (HYBE)",
    "ano_nascimento": 2005,
    "nacionalidade": "Coreana-Australiana",
    "posicao": [
      "Main Vocal"
    ],
    "altura_cm": 165
  },
  {
    "nome": "Haerin",
    "grupo": "NewJeans",
    "empresa": "ADOR (HYBE)",
    "ano_nascimento": 2006,
    "nacionalidade": "Coreana",
    "posicao": [
      "Lead Vocal",
      "Lead Dancer"
    ],
    "altura_cm": 164
  },
  {
    "nome": "Hyein",
    "grupo": "NewJeans",
    "empresa": "ADOR (HYBE)",
    "ano_nascimento": 2008,
    "nacionalidade": "Coreana",
    "posicao": [
      "Maknae",
      "Vocal"
    ],
    "altura_cm": 170
  },
  {
    "nome": "Irene",
    "grupo": "Red Velvet",
    "empresa": "SM Entertainment",
    "ano_nascimento": 1991,
    "nacionalidade": "Coreana",
    "posicao": [
      "Leader",
      "Main Rapper",
      "Visual"
    ],
    "altura_cm": 158
  },
  {
    "nome": "Seulgi",
    "grupo": "Red Velvet",
    "empresa": "SM Entertainment",
    "ano_nascimento": 1994,
    "nacionalidade": "Coreana",
    "posicao": [
      "Lead Vocal",
      "Main Dancer"
    ],
    "altura_cm": 161
  },
  {
    "nome": "Wendy",
    "grupo": "Red Velvet",
    "empresa": "SM Entertainment",
    "ano_nascimento": 1994,
    "nacionalidade": "Coreana",
    "posicao": [
      "Main Vocal",
      "Dancer",
      "Rapper"
    ],
    "altura_cm": 159
  },
  {
    "nome": "Joy",
    "grupo": "Red Velvet",
    "empresa": "SM Entertainment",
    "ano_nascimento": 1996,
    "nacionalidade": "Coreana",
    "posicao": [
      "Lead Vocal",
      "Rapper"
    ],
    "altura_cm": 167
  },
  {
    "nome": "Yeri",
    "grupo": "Red Velvet",
    "empresa": "SM Entertainment",
    "ano_nascimento": 1999,
    "nacionalidade": "Coreana",
    "posicao": [
      "Vocal",
      "Rapper",
      "Maknae"
    ],
    "altura_cm": 158
  },
  {
    "nome": "Jennie",
    "grupo": "BLACKPINK",
    "empresa": "YG Entertainment",
    "ano_nascimento": 1996,
    "nacionalidade": "Coreana",
    "posicao": [
      "Main Rapper",
      "Lead Vocal"
    ],
    "altura_cm": 163
  },
  {
    "nome": "Jisoo",
    "grupo": "BLACKPINK",
    "empresa": "YG Entertainment",
    "ano_nascimento": 1995,
    "nacionalidade": "Coreana",
    "posicao": [
      "Lead Vocal",
      "Visual"
    ],
    "altura_cm": 162
  },
  {
    "nome": "Rosé",
    "grupo": "BLACKPINK",
    "empresa": "YG Entertainment",
    "ano_nascimento": 1997,
    "nacionalidade": "Coreana-Nova Zelandesa",
    "posicao": [
      "Main Vocal",
      "Lead Vocal"
    ],
    "altura_cm": 168
  },
  {
    "nome": "Lisa",
    "grupo": "BLACKPINK",
    "empresa": "YG Entertainment",
    "ano_nascimento": 1997,
    "nacionalidade": "Tailandesa",
    "posicao": [
      "Lead Rapper",
      "Main Dancer",
      "Maknae"
    ],
    "altura_cm": 166
  },
  {
    "nome": "JiU",
    "grupo": "Dreamcatcher",
    "empresa": "Dreamcatcher Company",
    "ano_nascimento": 1994,
    "nacionalidade": "Coreana",
    "posicao": [
      "Leader",
      "Lead Vocal",
      "Visual"
    ],
    "altura_cm": 167
  },
  {
    "nome": "SuA",
    "grupo": "Dreamcatcher",
    "empresa": "Dreamcatcher Company",
    "ano_nascimento": 1994,
    "nacionalidade": "Coreana",
    "posicao": [
      "Main Dancer",
      "Vocal",
      "Lead Rapper"
    ],
    "altura_cm": 162
  },
  {
    "nome": "Siyeon",
    "grupo": "Dreamcatcher",
    "empresa": "Dreamcatcher Company",
    "ano_nascimento": 1995,
    "nacionalidade": "Coreana",
    "posicao": [
      "Main Vocal"
    ],
    "altura_cm": 166
  },
  {
    "nome": "Handong",
    "grupo": "Dreamcatcher",
    "empresa": "Dreamcatcher Company",
    "ano_nascimento": 1996,
    "nacionalidade": "Chinesa",
    "posicao": [
      "Vocal"
    ],
    "altura_cm": 165
  },
  {
    "nome": "Yoohyeon",
    "grupo": "Dreamcatcher",
    "empresa": "Dreamcatcher Company",
    "ano_nascimento": 1997,
    "nacionalidade": "Coreana",
    "posicao": [
      "Lead Dancer",
      "Lead Vocal"
    ],
    "altura_cm": 168
  },
  {
    "nome": "Dami",
    "grupo": "Dreamcatcher",
    "empresa": "Dreamcatcher Company",
    "ano_nascimento": 1997,
    "nacionalidade": "Coreana",
    "posicao": [
      "Main Rapper",
      "Lead Dancer"
    ],
    "altura_cm": 163
  },
  {
    "nome": "Gahyeon",
    "grupo": "Dreamcatcher",
    "empresa": "Dreamcatcher Company",
    "ano_nascimento": 1999,
    "nacionalidade": "Coreana",
    "posicao": [
      "Vocal",
      "Lead Rapper",
      "Maknae"
    ],
    "altura_cm": 160
  },
  {
    "nome": "Seola",
    "grupo": "WJSN",
    "empresa": "Starship Entertainment",
    "ano_nascimento": 1994,
    "nacionalidade": "Coreana",
    "posicao": [
      "Lead Vocal"
    ],
    "altura_cm": 164
  },
  {
    "nome": "Xuanyi",
    "grupo": "WJSN",
    "empresa": "Starship Entertainment",
    "ano_nascimento": 1995,
    "nacionalidade": "Chinesa",
    "posicao": [
      "Vocal",
      "Lead Dancer"
    ],
    "altura_cm": 166
  },
  {
    "nome": "Bona",
    "grupo": "WJSN",
    "empresa": "Starship Entertainment",
    "ano_nascimento": 1995,
    "nacionalidade": "Coreana",
    "posicao": [
      "Vocal",
      "Lead Dancer",
      "Visual"
    ],
    "altura_cm": 163
  },
  {
    "nome": "Soobin",
    "grupo": "WJSN",
    "empresa": "Starship Entertainment",
    "ano_nascimento": 1996,
    "nacionalidade": "Coreana",
    "posicao": [
      "Main Vocal"
    ],
    "altura_cm": 157
  },
  {
    "nome": "Luda",
    "grupo": "WJSN",
    "empresa": "Starship Entertainment",
    "ano_nascimento": 1997,
    "nacionalidade": "Coreana",
    "posicao": [
      "Vocal",
      "Rapper"
    ],
    "altura_cm": 156
  },
  {
    "nome": "Dawon",
    "grupo": "WJSN",
    "empresa": "Starship Entertainment",
    "ano_nascimento": 1997,
    "nacionalidade": "Coreana",
    "posicao": [
      "Main Vocal"
    ],
    "altura_cm": 167
  },
  {
    "nome": "Eunseo",
    "grupo": "WJSN",
    "empresa": "Starship Entertainment",
    "ano_nascimento": 1998,
    "nacionalidade": "Coreana",
    "posicao": [
      "Vocal",
      "Rapper"
    ],
    "altura_cm": 170
  },
  {
    "nome": "Cheng Xiao",
    "grupo": "WJSN",
    "empresa": "Starship Entertainment",
    "ano_nascimento": 1998,
    "nacionalidade": "Chinesa",
    "posicao": [
      "Main Dancer",
      "Face Of the Group",
      "Visual"
    ],
    "altura_cm": 166
  },
  {
    "nome": "Meiqi",
    "grupo": "WJSN",
    "empresa": "Starship Entertainment",
    "ano_nascimento": 1998,
    "nacionalidade": "Chinesa",
    "posicao": [
      "Main Dancer",
      "Vocal"
    ],
    "altura_cm": 165
  },
  {
    "nome": "Yeoreum",
    "grupo": "WJSN",
    "empresa": "Starship Entertainment",
    "ano_nascimento": 1999,
    "nacionalidade": "Coreana",
    "posicao": [
      "Rapper",
      "Main Dancer"
    ],
    "altura_cm": 162
  },
  {
    "nome": "Dayoung",
    "grupo": "WJSN",
    "empresa": "Starship Entertainment",
    "ano_nascimento": 1999,
    "nacionalidade": "Coreana",
    "posicao": [
      "Lead Vocal"
    ],
    "altura_cm": 161
  },
  {
    "nome": "Yeonjung",
    "grupo": "WJSN",
    "empresa": "Starship Entertainment",
    "ano_nascimento": 1999,
    "nacionalidade": "Coreana",
    "posicao": [
      "Main Vocal",
      "Maknae"
    ],
    "altura_cm": 165
  },
  {
    "nome": "Exy",
    "grupo": "WJSN",
    "empresa": "Starship Entertainment",
    "ano_nascimento": 1995,
    "nacionalidade": "Coreana",
    "posicao": [
      "Main Rapper",
      "Leader"
    ],
    "altura_cm": 166
  },
  {
    "nome": "Nayeon",
    "grupo": "TWICE",
    "empresa": "JYP Entertainment",
    "ano_nascimento": 1995,
    "nacionalidade": "Coreana",
    "posicao": [
      "Lead Vocal",
      "Face of the Group",
      "Center"
    ],
    "altura_cm": 163
  },
  {
    "nome": "Jeongyeon",
    "grupo": "TWICE",
    "empresa": "JYP Entertainment",
    "ano_nascimento": 1996,
    "nacionalidade": "Coreana",
    "posicao": [
      "Lead Vocal"
    ],
    "altura_cm": 167
  },
  {
    "nome": "Momo",
    "grupo": "TWICE",
    "empresa": "JYP Entertainment",
    "ano_nascimento": 1996,
    "nacionalidade": "Japonesa",
    "posicao": [
      "Main Dancer",
      "Rapper"
    ],
    "altura_cm": 163
  },
  {
    "nome": "Sana",
    "grupo": "TWICE",
    "empresa": "JYP Entertainment",
    "ano_nascimento": 1996,
    "nacionalidade": "Japonesa",
    "posicao": [
      "Vocal",
      "Visual",
      "Lead Dancer"
    ],
    "altura_cm": 163
  },
  {
    "nome": "Jihyo",
    "grupo": "TWICE",
    "empresa": "JYP Entertainment",
    "ano_nascimento": 1997,
    "nacionalidade": "Coreana",
    "posicao": [
      "Leader",
      "Main Vocal",
      "Lead Dancer"
    ],
    "altura_cm": 160
  },
  {
    "nome": "Mina",
    "grupo": "TWICE",
    "empresa": "JYP Entertainment",
    "ano_nascimento": 1997,
    "nacionalidade": "Japonesa",
    "posicao": [
      "Vocal",
      "Main Dancer",
      "Visual"
    ],
    "altura_cm": 163
  },
  {
    "nome": "Dahyun",
    "grupo": "TWICE",
    "empresa": "JYP Entertainment",
    "ano_nascimento": 1998,
    "nacionalidade": "Coreana",
    "posicao": [
      "Lead Rapper",
      "Vocal"
    ],
    "altura_cm": 161
  },
  {
    "nome": "Chaeyoung",
    "grupo": "TWICE",
    "empresa": "JYP Entertainment",
    "ano_nascimento": 1999,
    "nacionalidade": "Coreana",
    "posicao": [
      "Main Rapper",
      "Vocal"
    ],
    "altura_cm": 158
  },
  {
    "nome": "Tzuyu",
    "grupo": "TWICE",
    "empresa": "JYP Entertainment",
    "ano_nascimento": 1999,
    "nacionalidade": "Taiwanesa",
    "posicao": [
      "Vocal",
      "Visual",
      "Maknae"
    ],
    "altura_cm": 170
  },
  {
    "nome": "Soojin",
    "grupo": "Weeekly",
    "empresa": "IST Entertainment",
    "ano_nascimento": 2001,
    "nacionalidade": "Coreana",
    "posicao": [
      "Leader",
      "Visuall",
      "Main Dancer"
    ],
    "altura_cm": 165
  },
  {
    "nome": "Jiyoon",
    "grupo": "Weeekly",
    "empresa": "IST Entertainment",
    "ano_nascimento": 2002,
    "nacionalidade": "Coreana",
    "posicao": [
      "Vocal",
      "Rapper"
    ],
    "altura_cm": 165
  },
  {
    "nome": "Monday",
    "grupo": "Weeekly",
    "empresa": "IST Entertainment",
    "ano_nascimento": 2002,
    "nacionalidade": "Coreana",
    "posicao": [
      "Main Vocal",
      "Main Dancer",
      "Rapper"
    ],
    "altura_cm": 173
  },
  {
    "nome": "Soeun",
    "grupo": "Weeekly",
    "empresa": "IST Entertainment",
    "ano_nascimento": 2002,
    "nacionalidade": "Coreana",
    "posicao": [
      "Lead Vocal",
      "Main Dancer"
    ],
    "altura_cm": 171
  },
  {
    "nome": "Jaehee",
    "grupo": "Weeekly",
    "empresa": "IST Entertainment",
    "ano_nascimento": 2004,
    "nacionalidade": "Coreana",
    "posicao": [
      "Vocal",
      "Rapper"
    ],
    "altura_cm": 166
  },
  {
    "nome": "Jihan",
    "grupo": "Weeekly",
    "empresa": "IST Entertainment",
    "ano_nascimento": 2004,
    "nacionalidade": "Coreana",
    "posicao": [
      "Lead Vocal",
      "Visual",
      "Center"
    ],
    "altura_cm": 167
  },
  {
    "nome": "Zoa",
    "grupo": "Weeekly",
    "empresa": "IST Entertainment",
    "ano_nascimento": 2005,
    "nacionalidade": "Coreana",
    "posicao": [
      "Visual",
      "Rapper",
      "Maknae"
    ],
    "altura_cm": 171
  },
  {
    "nome": "Chorong",
    "grupo": "Apink",
    "empresa": "IST Entertainment",
    "ano_nascimento": 1991,
    "nacionalidade": "Coreana",
    "posicao": [
      "Leader",
      "Lead Dancer",
      "Vocal"
    ],
    "altura_cm": 162
  },
  {
    "nome": "Bomi",
    "grupo": "Apink",
    "empresa": "IST Entertainment",
    "ano_nascimento": 1993,
    "nacionalidade": "Coreana",
    "posicao": [
      "Main Dancer",
      "Main Rapper",
      "Center"
    ],
    "altura_cm": 163
  },
  {
    "nome": "Eunji",
    "grupo": "Apink",
    "empresa": "IST Entertainment",
    "ano_nascimento": 1993,
    "nacionalidade": "Coreana",
    "posicao": [
      "Main Vocal",
      "Face of the Group"
    ],
    "altura_cm": 162
  },
  {
    "nome": "Namjoo",
    "grupo": "Apink",
    "empresa": "IST Entertainment",
    "ano_nascimento": 1995,
    "nacionalidade": "Coreana",
    "posicao": [
      "Lead Vocal",
      "Lead Dancer",
      "Rapper"
    ],
    "altura_cm": 165
  },
  {
    "nome": "Hayoung",
    "grupo": "Apink",
    "empresa": "IST Entertainment",
    "ano_nascimento": 1996,
    "nacionalidade": "Coreana",
    "posicao": [
      "Vocal",
      "Rapper",
      "Maknae"
    ],
    "altura_cm": 169
  },
  {
    "nome": "Sihyeon",
    "grupo": "EVERGLOW",
    "empresa": "Yuehua Entertainment",
    "ano_nascimento": 1999,
    "nacionalidade": "Coreana",
    "posicao": [
      "Leader",
      "Main Vocal",
      "Face of the Group"
    ],
    "altura_cm": 170
  },
  {
    "nome": "E:U",
    "grupo": "EVERGLOW",
    "empresa": "Yuehua Entertainment",
    "ano_nascimento": 1998,
    "nacionalidade": "Coreana",
    "posicao": [
      "Main Rapper",
      "Main Dancer"
    ],
    "altura_cm": 161
  },
  {
    "nome": "Mia",
    "grupo": "EVERGLOW",
    "empresa": "Yuehua Entertainment",
    "ano_nascimento": 2000,
    "nacionalidade": "Coreana",
    "posicao": [
      "Main Vocal",
      "Main Dancer",
      "Rapper"
    ],
    "altura_cm": 163
  },
  {
    "nome": "Onda",
    "grupo": "EVERGLOW",
    "empresa": "Yuehua Entertainment",
    "ano_nascimento": 2000,
    "nacionalidade": "Coreana",
    "posicao": [
      "Lead Dancer"
    ],
    "altura_cm": 166
  },
  {
    "nome": "Aisha",
    "grupo": "EVERGLOW",
    "empresa": "Yuehua Entertainment",
    "ano_nascimento": 2000,
    "nacionalidade": "Coreana",
    "posicao": [
      "Face of the Group",
      "Lead Dancer",
      "Lead Rapper"
    ],
    "altura_cm": 174
  },
  {
    "nome": "Yiren",
    "grupo": "EVERGLOW",
    "empresa": "Yuehua Entertainment",
    "ano_nascimento": 2000,
    "nacionalidade": "Chinesa",
    "posicao": [
      "Visuall",
      "Center",
      "Maknae"
    ],
    "altura_cm": 163
  },
  {
    "nome": "Gyuri",
    "grupo": "KARA",
    "empresa": "DSP Media",
    "ano_nascimento": 1988,
    "nacionalidade": "Coreana",
    "posicao": [
      "Leader",
      "Lead Vocal"
    ],
    "altura_cm": 162
  },
  {
    "nome": "Seungyeon",
    "grupo": "KARA",
    "empresa": "DSP Media",
    "ano_nascimento": 1988,
    "nacionalidade": "Coreana",
    "posicao": [
      "Main Vocal"
    ],
    "altura_cm": 160
  },
  {
    "nome": "Nicole",
    "grupo": "KARA",
    "empresa": "DSP Media",
    "ano_nascimento": 1991,
    "nacionalidade": "Coreana-Americana",
    "posicao": [
      "Main Rapper",
      "Main Dancer",
      "Vocal"
    ],
    "altura_cm": 165
  },
  {
    "nome": "Jiyoung",
    "grupo": "KARA",
    "empresa": "DSP Media",
    "ano_nascimento": 1994,
    "nacionalidade": "Coreana",
    "posicao": [
      "Vocal",
      "Visual",
      "Maknae"
    ],
    "altura_cm": 167
  },
  {
    "nome": "Youngji",
    "grupo": "KARA",
    "empresa": "DSP Media",
    "ano_nascimento": 1994,
    "nacionalidade": "Coreana",
    "posicao": [
      "Main Rapper",
      "Maknae",
      "Lead Dancer"
    ],
    "altura_cm": 165
  },
  {
    "nome": "Yeeun",
    "grupo": "Wonder Girls",
    "empresa": "JYP Entertainment",
    "ano_nascimento": 1989,
    "nacionalidade": "Coreana",
    "posicao": [
      "Leader",
      "Main Vocal"
    ],
    "altura_cm": 165
  },
  {
    "nome": "Sunye",
    "grupo": "Wonder Girls",
    "empresa": "JYP Entertainment",
    "ano_nascimento": 1989,
    "nacionalidade": "Coreana",
    "posicao": [
      "Main Vocal"
    ],
    "altura_cm": 160
  },
  {
    "nome": "Sunmi",
    "grupo": "Wonder Girls",
    "empresa": "JYP Entertainment",
    "ano_nascimento": 1992,
    "nacionalidade": "Coreana",
    "posicao": [
      "Vocal",
      "Main Dancer",
      "Visual"
    ],
    "altura_cm": 166
  },
  {
    "nome": "Sohee",
    "grupo": "Wonder Girls",
    "empresa": "JYP Entertainment",
    "ano_nascimento": 1992,
    "nacionalidade": "Coreana",
    "posicao": [
      "Face of The Group",
      "Main Dancer",
      "Visual"
    ],
    "altura_cm": 163
  },
  {
    "nome": "Yubin",
    "grupo": "Wonder Girls",
    "empresa": "JYP Entertainment",
    "ano_nascimento": 1988,
    "nacionalidade": "Coreana",
    "posicao": [
      "Main Rapper",
      "Face of the Group",
      "Vocal"
    ],
    "altura_cm": 161
  },
  {
    "nome": "Hyelim",
    "grupo": "Wonder Girls",
    "empresa": "JYP Entertainment",
    "ano_nascimento": 1992,
    "nacionalidade": "Coreana",
    "posicao": [
      "Vocal",
      "Lead Rapper",
      "Maknae"
    ],
    "altura_cm": 165
  },
  {
    "nome": "Sowon",
    "grupo": "Gfriend",
    "empresa": "Source Music",
    "ano_nascimento": 1995,
    "nacionalidade": "Coreana",
    "posicao": [
      "Leader",
      "Vocal",
      "Visual"
    ],
    "altura_cm": 173
  },
  {
    "nome": "Yerin",
    "grupo": "Gfriend",
    "empresa": "Source Music",
    "ano_nascimento": 1996,
    "nacionalidade": "Coreana",
    "posicao": [
      "Center",
      "Lead Dancer",
      "Face of the Group"
    ],
    "altura_cm": 167
  },
  {
    "nome": "Eunha",
    "grupo": "Gfriend",
    "empresa": "Source Music",
    "ano_nascimento": 1997,
    "nacionalidade": "Coreana",
    "posicao": [
      "Lead Vocal"
    ],
    "altura_cm": 162
  },
  {
    "nome": "Yuju",
    "grupo": "Gfriend",
    "empresa": "Source Music",
    "ano_nascimento": 1997,
    "nacionalidade": "Coreana",
    "posicao": [
      "Main Vocal"
    ],
    "altura_cm": 169
  },
  {
    "nome": "SinB",
    "grupo": "Gfriend",
    "empresa": "Source Music",
    "ano_nascimento": 1998,
    "nacionalidade": "Coreana",
    "posicao": [
      "Main Dancer",
      "Center"
    ],
    "altura_cm": 166
  },
  {
    "nome": "Umji",
    "grupo": "Gfriend",
    "empresa": "Source Music",
    "ano_nascimento": 1998,
    "nacionalidade": "Coreana",
    "posicao": [
      "Vocal",
      "Maknae"
    ],
    "altura_cm": 164
  },
  {
    "nome": "Solar",
    "grupo": "MAMAMOO",
    "empresa": "RBW Entertainment",
    "ano_nascimento": 1991,
    "nacionalidade": "Coreana",
    "posicao": [
      "Leader",
      "Main Vocal"
    ],
    "altura_cm": 160
  },
  {
    "nome": "Moonbyul",
    "grupo": "MAMAMOO",
    "empresa": "RBW Entertainment",
    "ano_nascimento": 1992,
    "nacionalidade": "Coreana",
    "posicao": [
      "Main Rapper",
      "Dancer"
    ],
    "altura_cm": 163
  },
  {
    "nome": "Wheein",
    "grupo": "MAMAMOO",
    "empresa": "RBW Entertainment",
    "ano_nascimento": 1995,
    "nacionalidade": "Coreana",
    "posicao": [
      "Main Vocal"
    ],
    "altura_cm": 158
  },
  {
    "nome": "Hwasa",
    "grupo": "MAMAMOO",
    "empresa": "RBW Entertainment",
    "ano_nascimento": 1995,
    "nacionalidade": "Coreana",
    "posicao": [
      "Lead Vocal",
      "Rapper",
      "Maknae"
    ],
    "altura_cm": 160
  },
  {
    "nome": "Natty",
    "grupo": "KISS OF LIFE",
    "empresa": "S2 Entertainment",
    "ano_nascimento": 2002,
    "nacionalidade": "Tailandesa",
    "posicao": [
      "Vocal",
      "Main Dancer",
      "Lead Rapper"
    ],
    "altura_cm": 167
  },
  {
    "nome": "Julie",
    "grupo": "KISS OF LIFE",
    "empresa": "S2 Entertainment",
    "ano_nascimento": 2000,
    "nacionalidade": "Americana",
    "posicao": [
      "Leader",
      "Main Rapper",
      "Lead Dancer"
    ],
    "altura_cm": 163
  },
  {
    "nome": "Belle",
    "grupo": "KISS OF LIFE",
    "empresa": "S2 Entertainment",
    "ano_nascimento": 2004,
    "nacionalidade": "Coreana-Americana",
    "posicao": [
      "Main Vocal"
    ],
    "altura_cm": 168
  },
  {
    "nome": "Haneul",
    "grupo": "KISS OF LIFE",
    "empresa": "S2 Entertainment",
    "ano_nascimento": 2005,
    "nacionalidade": "Coreana",
    "posicao": [
      "Lead Vocal",
      "Maknae"
    ],
    "altura_cm": 169
  },
  {
    "nome": "Ruka",
    "grupo": "BABYMONSTER",
    "empresa": "YG Entertainment",
    "ano_nascimento": 2002,
    "nacionalidade": "Japonesa",
    "posicao": [
      "Main Dancer",
      "Main Rapper"
    ],
    "altura_cm": 165
  },
  {
    "nome": "Pharita",
    "grupo": "BABYMONSTER",
    "empresa": "YG Entertainment",
    "ano_nascimento": 2005,
    "nacionalidade": "Tailandesa",
    "posicao": [
      "Vocal"
    ],
    "altura_cm": 170
  },
  {
    "nome": "Asa",
    "grupo": "BABYMONSTER",
    "empresa": "YG Entertainment",
    "ano_nascimento": 2006,
    "nacionalidade": "Japonesa",
    "posicao": [
      "Main Rapper",
      "Dancer"
    ],
    "altura_cm": 167
  },
  {
    "nome": "Ahyeon",
    "grupo": "BABYMONSTER",
    "empresa": "YG Entertainment",
    "ano_nascimento": 2007,
    "nacionalidade": "Coreana",
    "posicao": [
      "Main Vocal",
      "Rapper",
      "Center"
    ],
    "altura_cm": 168
  },
  {
    "nome": "Rami",
    "grupo": "BABYMONSTER",
    "empresa": "YG Entertainment",
    "ano_nascimento": 2007,
    "nacionalidade": "Coreana",
    "posicao": [
      "Main Vocal"
    ],
    "altura_cm": 172
  },
  {
    "nome": "Rora",
    "grupo": "BABYMONSTER",
    "empresa": "YG Entertainment",
    "ano_nascimento": 2008,
    "nacionalidade": "Coreana",
    "posicao": [
      "Lead Vocal",
      "Visual"
    ],
    "altura_cm": 171
  },
  {
    "nome": "Chiquita",
    "grupo": "BABYMONSTER",
    "empresa": "YG Entertainment",
    "ano_nascimento": 2009,
    "nacionalidade": "Tailandesa",
    "posicao": [
      "Maknae",
      "Vocal",
      "Dancer"
    ],
    "altura_cm": 169
  },
  {
    "nome": "Taeyeon",
    "grupo": "Girls' Generation",
    "empresa": "SM Entertainment",
    "ano_nascimento": 1989,
    "nacionalidade": "Coreana",
    "posicao": [
      "Leader",
      "Main Vocal"
    ],
    "altura_cm": 160
  },
  {
    "nome": "Sunny",
    "grupo": "Girls' Generation",
    "empresa": "SM Entertainment",
    "ano_nascimento": 1989,
    "nacionalidade": "Coreana-Americana",
    "posicao": [
      "Lead Vocal"
    ],
    "altura_cm": 158
  },
  {
    "nome": "Tiffany",
    "grupo": "Girls' Generation",
    "empresa": "SM Entertainment",
    "ano_nascimento": 1989,
    "nacionalidade": "Coreana-Americana",
    "posicao": [
      "Lead Vocal"
    ],
    "altura_cm": 162
  },
  {
    "nome": "Hyoyeon",
    "grupo": "Girls' Generation",
    "empresa": "SM Entertainment",
    "ano_nascimento": 1989,
    "nacionalidade": "Coreana",
    "posicao": [
      "Main Dancer",
      "Main Rapper"
    ],
    "altura_cm": 161
  },
  {
    "nome": "Yuri",
    "grupo": "Girls' Generation",
    "empresa": "SM Entertainment",
    "ano_nascimento": 1989,
    "nacionalidade": "Coreana",
    "posicao": [
      "Lead Rapper",
      "Main Dancer",
      "Vocal"
    ],
    "altura_cm": 167
  },
  {
    "nome": "Sooyoung",
    "grupo": "Girls' Generation",
    "empresa": "SM Entertainment",
    "ano_nascimento": 1990,
    "nacionalidade": "Coreana",
    "posicao": [
      "Vocal",
      "Lead Dancer",
      "Lead Rapper"
    ],
    "altura_cm": 172
  },
  {
    "nome": "Yoona",
    "grupo": "Girls' Generation",
    "empresa": "SM Entertainment",
    "ano_nascimento": 1990,
    "nacionalidade": "Coreana",
    "posicao": [
      "Center",
      "Visual",
      "Lead Dancer"
    ],
    "altura_cm": 168
  },
  {
    "nome": "Seohyun",
    "grupo": "Girls' Generation",
    "empresa": "SM Entertainment",
    "ano_nascimento": 1991,
    "nacionalidade": "Coreana",
    "posicao": [
      "Lead Vocal",
      "Maknae"
    ],
    "altura_cm": 180
  },
  {
    "nome": "Fei",
    "grupo": "miss A",
    "empresa": "JYP Entertainment",
    "ano_nascimento": 1987,
    "nacionalidade": "Chinesa",
    "posicao": [
      "Main Vocal"
    ],
    "altura_cm": 164
  },
  {
    "nome": "Jia",
    "grupo": "miss A",
    "empresa": "JYP Entertainment",
    "ano_nascimento": 1989,
    "nacionalidade": "Chinesa",
    "posicao": [
      "Main Rapper",
      "Vocal",
      "Lead Dancer"
    ],
    "altura_cm": 164
  },
  {
    "nome": "Min",
    "grupo": "miss A",
    "empresa": "JYP Entertainment",
    "ano_nascimento": 1991,
    "nacionalidade": "Coreana",
    "posicao": [
      "Lead Vocal",
      "Main Dancer",
      "Lead Rapper"
    ],
    "altura_cm": 161
  },
  {
    "nome": "Suzy",
    "grupo": "miss A",
    "empresa": "JYP Entertainment",
    "ano_nascimento": 1994,
    "nacionalidade": "Coreana",
    "posicao": [
      "Face of The Group",
      "Visual",
      "Maknae"
    ],
    "altura_cm": 168
  },
  {
    "nome": "Yujin",
    "grupo": "Kep1er",
    "empresa": "WakeOne Entertainment",
    "ano_nascimento": 1996,
    "nacionalidade": "Coreana",
    "posicao": [
      "Leader",
      "Vocal"
    ],
    "altura_cm": 163
  },
  {
    "nome": "Xiaoting",
    "grupo": "Kep1er",
    "empresa": "WakeOne Entertainment",
    "ano_nascimento": 1999,
    "nacionalidade": "Chinesa",
    "posicao": [
      "Main Dancer",
      "Visual"
    ],
    "altura_cm": 168
  },
  {
    "nome": "Mashiro",
    "grupo": "Kep1er",
    "empresa": "WakeOne Entertainment",
    "ano_nascimento": 1999,
    "nacionalidade": "Japonesa",
    "posicao": [
      "Vocal"
    ],
    "altura_cm": 158
  },
  {
    "nome": "Chaehyun",
    "grupo": "Kep1er",
    "empresa": "WakeOne Entertainment",
    "ano_nascimento": 2002,
    "nacionalidade": "Coreana",
    "posicao": [
      "Main Vocal",
      "Center"
    ],
    "altura_cm": 161
  },
  {
    "nome": "Dayeon",
    "grupo": "Kep1er",
    "empresa": "WakeOne Entertainment",
    "ano_nascimento": 2003,
    "nacionalidade": "Coreana",
    "posicao": [
      "Vocal",
      "Main Dancer",
      "Main Rapper"
    ],
    "altura_cm": 158
  },
  {
    "nome": "Hikaru",
    "grupo": "Kep1er",
    "empresa": "WakeOne Entertainment",
    "ano_nascimento": 2004,
    "nacionalidade": "Japonesa",
    "posicao": [
      "Main Dancer",
      "Main Rapper"
    ],
    "altura_cm": 155
  },
  {
    "nome": "Bahiyyih",
    "grupo": "Kep1er",
    "empresa": "WakeOne Entertainment",
    "ano_nascimento": 2004,
    "nacionalidade": "Coreana-Americana",
    "posicao": [
      "Vocal"
    ],
    "altura_cm": 166
  },
  {
    "nome": "Youngeun",
    "grupo": "Kep1er",
    "empresa": "WakeOne Entertainment",
    "ano_nascimento": 2004,
    "nacionalidade": "Coreana",
    "posicao": [
      "Main Vocal",
      "Dancer"
    ],
    "altura_cm": 158
  },
  {
    "nome": "Yeseo",
    "grupo": "Kep1er",
    "empresa": "WakeOne Entertainment",
    "ano_nascimento": 2005,
    "nacionalidade": "Coreana",
    "posicao": [
      "Vocal",
      "Maknae"
    ],
    "altura_cm": 157
  },
  {
    "nome": "Minju",
    "grupo": "ILLIT",
    "empresa": "Belift Lab (HYBE)",
    "ano_nascimento": 2004,
    "nacionalidade": "Coreana",
    "posicao": [
      "Main Vocal"
    ],
    "altura_cm": 163
  },
  {
    "nome": "Moka",
    "grupo": "ILLIT",
    "empresa": "Belift Lab (HYBE)",
    "ano_nascimento": 2004,
    "nacionalidade": "Japonesa",
    "posicao": [
      "Lead Dancer"
    ],
    "altura_cm": 162
  },
  {
    "nome": "Wonhee",
    "grupo": "ILLIT",
    "empresa": "Belift Lab (HYBE)",
    "ano_nascimento": 2007,
    "nacionalidade": "Coreana",
    "posicao": [
      "Vocal"
    ],
    "altura_cm": 162
  },
  {
    "nome": "Iroha",
    "grupo": "ILLIT",
    "empresa": "Belift Lab (HYBE)",
    "ano_nascimento": 2008,
    "nacionalidade": "Japonesa",
    "posicao": [
      "Main Dancer",
      "Maknae"
    ],
    "altura_cm": 158
  },
  {
    "nome": "Yunah",
    "grupo": "ILLIT",
    "empresa": "Belift Lab (HYBE)",
    "ano_nascimento": 2004,
    "nacionalidade": "Coreana",
    "posicao": [
      "Leader",
      "Lead Vocal"
    ],
    "altura_cm": 168
  },
  {
    "nome": "Sunhye",
    "grupo": "Young Posse",
    "empresa": "DSP Media",
    "ano_nascimento": 2004,
    "nacionalidade": "Coreana",
    "posicao": [
      "Leader",
      "Main Rapper",
      "Lead Dancer"
    ],
    "altura_cm": 159
  },
  {
    "nome": "Yeonjung",
    "grupo": "Young Posse",
    "empresa": "DSP Media",
    "ano_nascimento": 2004,
    "nacionalidade": "Coreana",
    "posicao": [
      "Main Dancer",
      "Lead Rapper"
    ],
    "altura_cm": 162
  },
  {
    "nome": "Jiana",
    "grupo": "Young Posse",
    "empresa": "DSP Media",
    "ano_nascimento": 2006,
    "nacionalidade": "Coreana",
    "posicao": [
      "Main Vocal"
    ],
    "altura_cm": 163
  },
  {
    "nome": "Doeun",
    "grupo": "Young Posse",
    "empresa": "DSP Media",
    "ano_nascimento": 2007,
    "nacionalidade": "Coreana",
    "posicao": [
      "Lead Dancer",
      "Lead Rapper"
    ],
    "altura_cm": 168
  },
  {
    "nome": "Jieun",
    "grupo": "Young Posse",
    "empresa": "DSP Media",
    "ano_nascimento": 2007,
    "nacionalidade": "Coreana",
    "posicao": [
      "Lead Dancer",
      "Maknae",
      "Vocal"
    ],
    "altura_cm": 157
  },
  {
    "nome": "Woni",
    "grupo": "Rescene",
    "empresa": "THE MUZE Entertainment",
    "ano_nascimento": 2004,
    "nacionalidade": "Coreana",
    "posicao": [
      "Leader",
      "Main Rapper",
      "Visual"
    ],
    "altura_cm": 165
  },
  {
    "nome": "Liv",
    "grupo": "Rescene",
    "empresa": "THE MUZE Entertainment",
    "ano_nascimento": 2006,
    "nacionalidade": "Coreana",
    "posicao": [
      "Main Vocal",
      "Dancer"
    ],
    "altura_cm": 164
  },
  {
    "nome": "Minami",
    "grupo": "Rescene",
    "empresa": "THE MUZE Entertainment",
    "ano_nascimento": 2006,
    "nacionalidade": "Japonesa",
    "posicao": [
      "Main Vocal",
      "Lead Dancer",
      "Rapper"
    ],
    "altura_cm": 163
  },
  {
    "nome": "May",
    "grupo": "Rescene",
    "empresa": "THE MUZE Entertainment",
    "ano_nascimento": 2008,
    "nacionalidade": "Coreana",
    "posicao": [
      "Vocal",
      "Lead Dancer"
    ],
    "altura_cm": 165
  },
  {
    "nome": "Zena",
    "grupo": "Rescene",
    "empresa": "THE MUZE Entertainment",
    "ano_nascimento": 2008,
    "nacionalidade": "Coreana",
    "posicao": [
      "Main Dancer",
      "Lead Vocal",
      "Maknae"
    ],
    "altura_cm": 164
  },
  [
    {
      "nome": "Jiyu",
      "grupo": "KiiiKiii",
      "empresa": "Starship Entertainment",
      "ano_nascimento": 2006,
      "nacionalidade": "Coreana",
      "posicao": [
        "Leader",
        "Vocal",
        "Dancer"
      ],
      "altura_cm": 159
    },
    {
      "nome": "Leesol",
      "grupo": "KiiiKiii",
      "empresa": "Starship Entertainment",
      "ano_nascimento": 2005,
      "nacionalidade": "Coreana",
      "posicao": [
        "Main Rapper",
        "Vocal"
      ],
      "altura_cm": 166
    },
    {
      "nome": "Sui",
      "grupo": "KiiiKiii",
      "empresa": "Starship Entertainment",
      "ano_nascimento": 2006,
      "nacionalidade": "Coreana",
      "posicao": [
        "Main Vocal"
      ],
      "altura_cm": 170
    },
    {
      "nome": "Haum",
      "grupo": "KiiiKiii",
      "empresa": "Starship Entertainment",
      "ano_nascimento": 2006,
      "nacionalidade": "Coreana",
      "posicao": [
        "Vocal",
        "Dancer",
        "Visual"
      ],
      "altura_cm": 163
    },
    {
      "nome": "Kya",
      "grupo": "KiiiKiii",
      "empresa": "Starship Entertainment",
      "ano_nascimento": 2010,
      "nacionalidade": "Coreana",
      "posicao": [
        "Vocal",
        "Maknae"
      ],
      "altura_cm": 168
    }
  ],
  [
    {
      "nome": "Carmen",
      "grupo": "Hearts2Hearts",
      "empresa": "SM Entertainment",
      "ano_nascimento": 2006,
      "nacionalidade": "Indonésia",
      "posicao": [
        "Vocal"
      ],
      "altura_cm": 168
    },
    {
      "nome": "Jiwoo",
      "grupo": "Hearts2Hearts",
      "empresa": "SM Entertainment",
      "ano_nascimento": 2006,
      "nacionalidade": "Coreana",
      "posicao": [
        "Leader",
        "Dancer",
        "Visual"
      ],
      "altura_cm": 170
    },
    {
      "nome": "Yuha",
      "grupo": "Hearts2Hearts",
      "empresa": "SM Entertainment",
      "ano_nascimento": 2007,
      "nacionalidade": "Coreana",
      "posicao": [
        "Vocal",
        "Dancer"
      ],
      "altura_cm": 164
    },
    {
      "nome": "Stella",
      "grupo": "Hearts2Hearts",
      "empresa": "SM Entertainment",
      "ano_nascimento": 2007,
      "nacionalidade": "Coreana",
      "posicao": [
        "Vocal"
      ],
      "altura_cm": 167
    },
    {
      "nome": "Juun",
      "grupo": "Hearts2Hearts",
      "empresa": "SM Entertainment",
      "ano_nascimento": 2008,
      "nacionalidade": "Coreana",
      "posicao": [
        "Main Dancer",
        "Rapper"
      ],
      "altura_cm": 165
    },
    {
      "nome": "Ana",
      "grupo": "Hearts2Hearts",
      "empresa": "SM Entertainment",
      "ano_nascimento": 2008,
      "nacionalidade": "Coreana",
      "posicao": [
        "Lead Vocal",
        "Visual"
      ],
      "altura_cm": 169
    },
    {
      "nome": "Ian",
      "grupo": "Hearts2Hearts",
      "empresa": "SM Entertainment",
      "ano_nascimento": 2009,
      "nacionalidade": "Coreana",
      "posicao": [
        "Visual",
        "Center"
      ],
      "altura_cm": 165
    },
    {
      "nome": "Yeon",
      "grupo": "Hearts2Hearts",
      "empresa": "SM Entertainment",
      "ano_nascimento": 2010,
      "nacionalidade": "Coreana",
      "posicao": [
        "Vocal",
        "Maknae"
      ],
      "altura_cm": 166
    }
  ],
  {
    "nome": "Soohee",
    "grupo": "Billlie",
    "empresa": "Mystic Story",
    "ano_nascimento": 2000,
    "nacionalidade": "Coreana",
    "posicao": [
      "Vocal"
    ],
    "altura_cm": 161
  },
  {
    "nome": "Siyoon",
    "grupo": "Billlie",
    "empresa": "Mystic Story",
    "ano_nascimento": 2000,
    "nacionalidade": "Coreana",
    "posicao": [
      "Vocal",
      "Rapper"
    ],
    "altura_cm": 163
  },
  {
    "nome": "Tsuki",
    "grupo": "Billlie",
    "empresa": "Mystic Story",
    "ano_nascimento": 2002,
    "nacionalidade": "Japonesa",
    "posicao": [
      "Main Dancer",
      "Vocal"
    ],
    "altura_cm": 164
  },
  {
    "nome": "Moon Sua",
    "grupo": "Billlie",
    "empresa": "Mystic Story",
    "ano_nascimento": 1999,
    "nacionalidade": "Coreana",
    "posicao": [
      "Main Rapper",
      "Vocal"
    ],
    "altura_cm": 164
  },
  {
    "nome": "Haram",
    "grupo": "Billlie",
    "empresa": "Mystic Story",
    "ano_nascimento": 2001,
    "nacionalidade": "Coreana",
    "posicao": [
      "Main Vocal"
    ],
    "altura_cm": 162
  },
  {
    "nome": "Sheon",
    "grupo": "Billlie",
    "empresa": "Mystic Story",
    "ano_nascimento": 2003,
    "nacionalidade": "Coreana",
    "posicao": [
      "Vocal",
      "Dancer"
    ],
    "altura_cm": 165
  },
  {
    "nome": "Haruna",
    "grupo": "Billlie",
    "empresa": "Mystic Story",
    "ano_nascimento": 2006,
    "nacionalidade": "Japonesa",
    "posicao": [
      "Vocal",
      "Maknae"
    ],
    "altura_cm": 160
  },
  {
    "nome": "Seolhee",
    "grupo": "H1-KEY",
    "empresa": "GLG",
    "ano_nascimento": 1998,
    "nacionalidade": "Coreana",
    "posicao": [
      "Leader",
      "Vocal"
    ],
    "altura_cm": 165
  },
  {
    "nome": "Riina",
    "grupo": "H1-KEY",
    "empresa": "GLG",
    "ano_nascimento": 2001,
    "nacionalidade": "Coreana",
    "posicao": [
      "Vocal"
    ],
    "altura_cm": 164
  },
  {
    "nome": "Hwiseo",
    "grupo": "H1-KEY",
    "empresa": "GLG",
    "ano_nascimento": 2002,
    "nacionalidade": "Coreana",
    "posicao": [
      "Main Vocal"
    ],
    "altura_cm": 162
  },
  {
    "nome": "Yel",
    "grupo": "H1-KEY",
    "empresa": "GLG",
    "ano_nascimento": 2004,
    "nacionalidade": "Coreana",
    "posicao": [
      "Vocal",
      "Rapper",
      "Maknae"
    ],
    "altura_cm": 170
  },
  {
    "nome": "Solji",
    "grupo": "EXID",
    "empresa": "Banana Culture",
    "ano_nascimento": 1989,
    "nacionalidade": "Coreana",
    "posicao": [
      "Leader",
      "Main Vocal"
    ],
    "altura_cm": 170
  },
  {
    "nome": "LE",
    "grupo": "EXID",
    "empresa": "Banana Culture",
    "ano_nascimento": 1991,
    "nacionalidade": "Coreana",
    "posicao": [
      "Main Rapper"
    ],
    "altura_cm": 168
  },
  {
    "nome": "Hani",
    "grupo": "EXID",
    "empresa": "Banana Culture",
    "ano_nascimento": 1992,
    "nacionalidade": "Coreana",
    "posicao": [
      "Vocal",
      "Visual"
    ],
    "altura_cm": 168
  },
  {
    "nome": "Hyerin",
    "grupo": "EXID",
    "empresa": "Banana Culture",
    "ano_nascimento": 1993,
    "nacionalidade": "Coreana",
    "posicao": [
      "Vocal"
    ],
    "altura_cm": 165
  },
  {
    "nome": "Jeonghwa",
    "grupo": "EXID",
    "empresa": "Banana Culture",
    "ano_nascimento": 1995,
    "nacionalidade": "Coreana",
    "posicao": [
      "Main Dancer",
      "Rapper",
      "Maknae"
    ],
    "altura_cm": 169
  },
  {
    "nome": "Keena",
    "grupo": "FIFTY FIFTY",
    "empresa": "ATTRAKT",
    "ano_nascimento": 2002,
    "nacionalidade": "Coreana",
    "posicao": [
      "Rapper",
      "Vocal"
    ],
    "altura_cm": 164
  },
  {
    "nome": "Chanelle",
    "grupo": "FIFTY FIFTY",
    "empresa": "ATTRAKT",
    "ano_nascimento": 2003,
    "nacionalidade": "Coreana-Americana",
    "posicao": [
      "Vocal"
    ],
    "altura_cm": 165
  },
  {
    "nome": "Yewon",
    "grupo": "FIFTY FIFTY",
    "empresa": "ATTRAKT",
    "ano_nascimento": 2005,
    "nacionalidade": "Coreana",
    "posicao": [
      "Vocal"
    ],
    "altura_cm": 160
  },
  {
    "nome": "Hana",
    "grupo": "FIFTY FIFTY",
    "empresa": "ATTRAKT",
    "ano_nascimento": 2006,
    "nacionalidade": "Coreana",
    "posicao": [
      "Vocal",
      "Maknae"
    ],
    "altura_cm": 166
  },
  {
    "nome": "Athena",
    "grupo": "FIFTY FIFTY",
    "empresa": "ATTRAKT",
    "ano_nascimento": 2007,
    "nacionalidade": "Coreana-Sueca",
    "posicao": [
      "Vocal",
      "Maknae"
    ],
    "altura_cm": 166
  },
  {
    "nome": "Miyeon",
    "grupo": "(G)I-DLE",
    "empresa": "Cube Entertainment",
    "ano_nascimento": 1997,
    "nacionalidade": "Coreana",
    "posicao": [
      "Main Vocal",
      "Visual"
    ],
    "altura_cm": 161
  },
  {
    "nome": "Minnie",
    "grupo": "(G)I-DLE",
    "empresa": "Cube Entertainment",
    "ano_nascimento": 1997,
    "nacionalidade": "Tailandesa",
    "posicao": [
      "Main Vocal"
    ],
    "altura_cm": 167
  },
  {
    "nome": "Soojin",
    "grupo": "(G)I-DLE",
    "empresa": "Cube Entertainment",
    "ano_nascimento": 1998,
    "nacionalidade": "Coreana",
    "posicao": [
      "Main Dancer",
      "Vocal"
    ],
    "altura_cm": 164
  },
  {
    "nome": "Soyeon",
    "grupo": "(G)I-DLE",
    "empresa": "Cube Entertainment",
    "ano_nascimento": 1998,
    "nacionalidade": "Coreana",
    "posicao": [
      "Leader",
      "Main Rapper",
      "Center"
    ],
    "altura_cm": 157
  },
  {
    "nome": "Yuqi",
    "grupo": "(G)I-DLE",
    "empresa": "Cube Entertainment",
    "ano_nascimento": 1999,
    "nacionalidade": "Chinesa",
    "posicao": [
      "Lead Vocal",
      "Main Dancer",
      "Face of the Group"
    ],
    "altura_cm": 163
  },
  {
    "nome": "Shuhua",
    "grupo": "(G)I-DLE",
    "empresa": "Cube Entertainment",
    "ano_nascimento": 2000,
    "nacionalidade": "Taiwanesa",
    "posicao": [
      "Vocal",
      "Maknae",
      "Visual"
    ],
    "altura_cm": 161
  },
  {
    "nome": "Mai",
    "grupo": "izna",
    "empresa": "WakeOne Entertainment",
    "ano_nascimento": 2004,
    "nacionalidade": "Japonesa",
    "posicao": [
      "Vocal"
    ],
    "altura_cm": 167
  },
  {
    "nome": "Jeemin",
    "grupo": "izna",
    "empresa": "WakeOne Entertainment",
    "ano_nascimento": 2005,
    "nacionalidade": "Coreana",
    "posicao": [
      "Center"
    ],
    "altura_cm": 172
  },
  {
    "nome": "Koko",
    "grupo": "izna",
    "empresa": "WakeOne Entertainment",
    "ano_nascimento": 2006,
    "nacionalidade": "Japonesa",
    "posicao": [
      " Main Dancer"
    ],
    "altura_cm": 174
  },
  {
    "nome": "Ryu Sarang",
    "grupo": "izna",
    "empresa": "WakeOne Entertainment",
    "ano_nascimento": 2007,
    "nacionalidade": "Coreana",
    "posicao": [
      "Vocal"
    ],
    "altura_cm": 162
  },
  {
    "nome": "Jungeun",
    "grupo": "izna",
    "empresa": "WakeOne Entertainment",
    "ano_nascimento": 2007,
    "nacionalidade": "Coreana",
    "posicao": [
      "Main Vocal"
    ],
    "altura_cm": 170
  },
  {
    "nome": "Saebi",
    "grupo": "izna",
    "empresa": "WakeOne Entertainment",
    "ano_nascimento": 2008,
    "nacionalidade": "Coreana",
    "posicao": [
      "Maknae"
    ],
    "altura_cm": 172
  },
  {
    "nome": "Jiyoon",
    "grupo": "izna",
    "empresa": "WakeOne Entertainment",
    "ano_nascimento": 2007,
    "nacionalidade": "Coreana",
    "posicao": [
      "Main Vocal"
    ],
    "altura_cm": 166
  },
  [
    {
      "nome": "Sooin",
      "grupo": "MEOVV",
      "empresa": "The Black Label",
      "ano_nascimento": 2005,
      "nacionalidade": "Coreana",
      "posicao": [
        "Main Dancer",
        "Vocal"
      ],
      "altura_cm": 172
    },
    {
      "nome": "Gawon",
      "grupo": "MEOVV",
      "empresa": "The Black Label",
      "ano_nascimento": 2005,
      "nacionalidade": "Coreana-Americana",
      "posicao": [
        "Main Vocal",
        "Rapper"
      ],
      "altura_cm": 173
    },
    {
      "nome": "Anna",
      "grupo": "MEOVV",
      "empresa": "The Black Label",
      "ano_nascimento": 2005,
      "nacionalidade": "Japonesa",
      "posicao": [
        "Vocal",
        "Visual"
      ],
      "altura_cm": 164
    },
    {
      "nome": "Narin",
      "grupo": "MEOVV",
      "empresa": "The Black Label",
      "ano_nascimento": 2007,
      "nacionalidade": "Coreana",
      "posicao": [
        "Main Rapper",
        "Main Vocal"
      ],
      "altura_cm": 166
    },
    {
      "nome": "Ella",
      "grupo": "MEOVV",
      "empresa": "The Black Label",
      "ano_nascimento": 2008,
      "nacionalidade": "Americana",
      "posicao": [
        "Vocal",
        "Visual",
        "Maknae"
      ],
      "altura_cm": 168
    }
  ],
  {
    "nome": "Hyein",
    "grupo": "MOMOLAND",
    "empresa": "MLD Entertainment",
    "ano_nascimento": 1998,
    "nacionalidade": "Coreana",
    "posicao": [
      "Vocal"
    ],
    "altura_cm": 164
  },
  {
    "nome": "Daisy",
    "grupo": "MOMOLAND",
    "empresa": "MLD Entertainment",
    "ano_nascimento": 1999,
    "nacionalidade": "Coreana-Canadense",
    "posicao": [
      "Main Rapper"
    ],
    "altura_cm": 162
  },
  {
    "nome": "JooE",
    "grupo": "MOMOLAND",
    "empresa": "MLD Entertainment",
    "ano_nascimento": 1999,
    "nacionalidade": "Coreana",
    "posicao": [
      "Rapper",
      "Dancer",
      "Vocal"
    ],
    "altura_cm": 164
  },
  {
    "nome": "Ahin",
    "grupo": "MOMOLAND",
    "empresa": "MLD Entertainment",
    "ano_nascimento": 1999,
    "nacionalidade": "Coreana",
    "posicao": [
      "Main Vocal"
    ],
    "altura_cm": 160
  },
  {
    "nome": "Nancy",
    "grupo": "MOMOLAND",
    "empresa": "MLD Entertainment",
    "ano_nascimento": 2000,
    "nacionalidade": "Coreana-Americana",
    "posicao": [
      "Vocal",
      "Visual",
      "Maknae"
    ],
    "altura_cm": 162
  },
  {
    "nome": "Hyojung",
    "grupo": "OH MY GIRL",
    "empresa": "WM Entertainment",
    "ano_nascimento": 1994,
    "nacionalidade": "Coreana",
    "posicao": [
      "Leader",
      "Main Vocal"
    ],
    "altura_cm": 158
  },
  {
    "nome": "JinE",
    "grupo": "OH MY GIRL",
    "empresa": "WM Entertainment",
    "ano_nascimento": 1995,
    "nacionalidade": "Coreana",
    "posicao": [
      "Vocal"
    ],
    "altura_cm": 160
  },
  {
    "nome": "Mimi",
    "grupo": "OH MY GIRL",
    "empresa": "WM Entertainment",
    "ano_nascimento": 1995,
    "nacionalidade": "Coreana",
    "posicao": [
      "Main Rapper"
    ],
    "altura_cm": 159
  },
  {
    "nome": "YooA",
    "grupo": "OH MY GIRL",
    "empresa": "WM Entertainment",
    "ano_nascimento": 1995,
    "nacionalidade": "Coreana",
    "posicao": [
      "Vocal",
      "Main Dancer"
    ],
    "altura_cm": 160
  },
  {
    "nome": "Seunghee",
    "grupo": "OH MY GIRL",
    "empresa": "WM Entertainment",
    "ano_nascimento": 1996,
    "nacionalidade": "Coreana",
    "posicao": [
      "Main Vocal"
    ],
    "altura_cm": 160
  },
  {
    "nome": "Jiho",
    "grupo": "OH MY GIRL",
    "empresa": "WM Entertainment",
    "ano_nascimento": 1997,
    "nacionalidade": "Coreana",
    "posicao": [
      "Vocal",
      "Visual"
    ],
    "altura_cm": 165
  },
  {
    "nome": "Binnie",
    "grupo": "OH MY GIRL",
    "empresa": "WM Entertainment",
    "ano_nascimento": 1997,
    "nacionalidade": "Coreana",
    "posicao": [
      "Vocal"
    ],
    "altura_cm": 159
  },
  {
    "nome": "Arin",
    "grupo": "OH MY GIRL",
    "empresa": "WM Entertainment",
    "ano_nascimento": 1999,
    "nacionalidade": "Coreana",
    "posicao": [
      "Vocal",
      "Maknae"
    ],
    "altura_cm": 165
  },
  {
    "nome": "CL",
    "grupo": "2NE1",
    "empresa": "YG Entertainment",
    "ano_nascimento": 1991,
    "nacionalidade": "Coreana",
    "posicao": [
      "Leader",
      "Main Rapper",
      "Vocal"
    ],
    "altura_cm": 162
  },
  {
    "nome": "Bom",
    "grupo": "2NE1",
    "empresa": "YG Entertainment",
    "ano_nascimento": 1984,
    "nacionalidade": "Coreana",
    "posicao": [
      "Main Vocal"
    ],
    "altura_cm": 165
  },
  {
    "nome": "Dara",
    "grupo": "2NE1",
    "empresa": "YG Entertainment",
    "ano_nascimento": 1984,
    "nacionalidade": "Coreana",
    "posicao": [
      "Vocal",
      "Visual"
    ],
    "altura_cm": 162
  },
  {
    "nome": "Minzy",
    "grupo": "2NE1",
    "empresa": "YG Entertainment",
    "ano_nascimento": 1994,
    "nacionalidade": "Coreana",
    "posicao": [
      "Main Dancer",
      "Vocal",
      "Maknae"
    ],
    "altura_cm": 161
  },
  {
    "nome": "Seoyeon",
    "grupo": "TripleS",
    "empresa": "Modhaus",
    "ano_nascimento": 2003,
    "nacionalidade": "Coreana",
    "posicao": [
      "Leader",
      "Vocal"
    ],
    "altura_cm": 160
  },
  {
    "nome": "Hyerin",
    "grupo": "TripleS",
    "empresa": "Modhaus",
    "ano_nascimento": 2007,
    "nacionalidade": "Coreana",
    "posicao": [
      "Lead Dancer"
    ],
    "altura_cm": 162
  },
  {
    "nome": "Jiwoo",
    "grupo": "TripleS",
    "empresa": "Modhaus",
    "ano_nascimento": 2005,
    "nacionalidade": "Coreana",
    "posicao": [
      "Main Vocal"
    ],
    "altura_cm": 173
  },
  {
    "nome": "Chaeyeon",
    "grupo": "TripleS",
    "empresa": "Modhaus",
    "ano_nascimento": 2004,
    "nacionalidade": "Coreana",
    "posicao": [
      "Vocal"
    ],
    "altura_cm": 171
  },
  {
    "nome": "Yooyeon",
    "grupo": "TripleS",
    "empresa": "Modhaus",
    "ano_nascimento": 2001,
    "nacionalidade": "Coreana",
    "posicao": [
      "Visual",
      "Center"
    ],
    "altura_cm": 165
  },
  {
    "nome": "Soomin",
    "grupo": "TripleS",
    "empresa": "Modhaus",
    "ano_nascimento": 2007,
    "nacionalidade": "Coreana",
    "posicao": [
      "Vocal",
      "Visual"
    ],
    "altura_cm": 161
  },
  {
    "nome": "Nakyoung",
    "grupo": "TripleS",
    "empresa": "Modhaus",
    "ano_nascimento": 2002,
    "nacionalidade": "Coreana",
    "posicao": [
      "Main Dancer",
      "Main Rapper",
      "Lead Vocal"
    ],
    "altura_cm": 166
  },
  {
    "nome": "Yubin",
    "grupo": "TripleS",
    "empresa": "Modhaus",
    "ano_nascimento": 2005,
    "nacionalidade": "Coreana",
    "posicao": [
      "Main Dancer",
      "Center"
    ],
    "altura_cm": 164
  },
  {
    "nome": "Kaede",
    "grupo": "TripleS",
    "empresa": "Modhaus",
    "ano_nascimento": 2005,
    "nacionalidade": "Japonesa",
    "posicao": [
      "Main Dancer",
      "Lead Vocal",
      "Center"
    ],
    "altura_cm": 161
  },
  {
    "nome": "Dahyun",
    "grupo": "TripleS",
    "empresa": "Modhaus",
    "ano_nascimento": 2003,
    "nacionalidade": "Coreana",
    "posicao": [
      "Main Vocal"
    ],
    "altura_cm": 160
  },
  {
    "nome": "Kotone",
    "grupo": "TripleS",
    "empresa": "Modhaus",
    "ano_nascimento": 2004,
    "nacionalidade": "Japonesa",
    "posicao": [
      "Main Dancer",
      "Main Rapper"
    ],
    "altura_cm": 162
  },
  {
    "nome": "Yeonji",
    "grupo": "TripleS",
    "empresa": "Modhaus",
    "ano_nascimento": 2008,
    "nacionalidade": "Coreana",
    "posicao": [
      "Dancer"
    ],
    "altura_cm": 163
  },
  {
    "nome": "Nien",
    "grupo": "TripleS",
    "empresa": "Modhaus",
    "ano_nascimento": 2003,
    "nacionalidade": "Taiwan",
    "posicao": [
      "Lead Dancer"
    ],
    "altura_cm": 169
  },
  {
    "nome": "Sohyun",
    "grupo": "TripleS",
    "empresa": "Modhaus",
    "ano_nascimento": 2002,
    "nacionalidade": "Coreana",
    "posicao": [
      "Lead Dancer",
      "Lead Rapper"
    ],
    "altura_cm": 167
  },
  {
    "nome": "Xinyu",
    "grupo": "TripleS",
    "empresa": "Modhaus",
    "ano_nascimento": 2002,
    "nacionalidade": "Chinesa",
    "posicao": [
      "Visual",
      "Vocal"
    ],
    "altura_cm": 174
  },
  {
    "nome": "Mayu",
    "grupo": "TripleS",
    "empresa": "Modhaus",
    "ano_nascimento": 2002,
    "nacionalidade": "Japonesa",
    "posicao": [
      "Lead Vocal"
    ],
    "altura_cm": 160
  },
  {
    "nome": "Lynn",
    "grupo": "TripleS",
    "empresa": "Modhaus",
    "ano_nascimento": 2006,
    "nacionalidade": "Japonesa",
    "posicao": [
      "Main Dancer",
      "Lead Rapper"
    ],
    "altura_cm": 171
  },
  {
    "nome": "JooBin",
    "grupo": "TripleS",
    "empresa": "Modhaus",
    "ano_nascimento": 2008,
    "nacionalidade": "Coreana",
    "posicao": [
      "Visual",
      "Vocal"
    ],
    "altura_cm": 168
  },
  {
    "nome": "Hayeon",
    "grupo": "TripleS",
    "empresa": "Modhaus",
    "ano_nascimento": 2007,
    "nacionalidade": "Coreana",
    "posicao": [
      "Lead Vocal",
      "Dancer"
    ],
    "altura_cm": 166
  },
  {
    "nome": "Shion",
    "grupo": "TripleS",
    "empresa": "Modhaus",
    "ano_nascimento": 2006,
    "nacionalidade": "Coreana",
    "posicao": [
      "Main Vocal"
    ],
    "altura_cm": 166
  },
  {
    "nome": "Chaewon",
    "grupo": "TripleS",
    "empresa": "Modhaus",
    "ano_nascimento": 2007,
    "nacionalidade": "Coreana",
    "posicao": [
      "Vocal"
    ],
    "altura_cm": 163
  },
  {
    "nome": "Sullin",
    "grupo": "TripleS",
    "empresa": "Modhaus",
    "ano_nascimento": 2006,
    "nacionalidade": "Tailandesa",
    "posicao": [
      "Vocal"
    ],
    "altura_cm": 169
  },
  {
    "nome": "Seoah",
    "grupo": "TripleS",
    "empresa": "Modhaus",
    "ano_nascimento": 2010,
    "nacionalidade": "Coreana",
    "posicao": [
      "Maknae",
      "Lead Vocal"
    ],
    "altura_cm": 158
  },
  {
    "nome": "Jiyeon",
    "grupo": "TripleS",
    "empresa": "Modhaus",
    "ano_nascimento": 2004,
    "nacionalidade": "Coreana",
    "posicao": [
      "Lead Dancer"
    ],
    "altura_cm": 167
  }
]